{
  "generated": "2026-03-18T23:46:00.754292",
  "tool": "Evidence Exhibit Packager (#92)",
  "total_exhibits": 200,
  "filings": {
    "F1": {
      "name": "Emergency Parenting Time",
      "exhibit_count": 20,
      "exhibits": [
        {
          "exhibit_num": 1,
          "bates": "PIGORS-F1-0001",
          "text_preview": "hearing  and\nsubpoenaed\n the  \nwhich  occurred  on 1 1/26/25.\nLaw\nIf a \nparenting  \ntime \nmodification\n \ndoes  not change  the \nchild's  \nestablished\n \ncustodial\nenvironment,\n the parenting  time  mod",
          "source": "3"
        },
        {
          "exhibit_num": 2,
          "bates": "PIGORS-F1-0002",
          "text_preview": "hearing  and  subpoenaed\n the  two\nhealth  west  staff  for  the next  hearing,  which  occurred  on 1 1/26/25.  At that  hearing,  the  two\nworkstestified,\n \nwas\nDespite  numerous\n warnings,  the Fat",
          "source": "7"
        },
        {
          "exhibit_num": 3,
          "bates": "PIGORS-F1-0003",
          "text_preview": "hearing  on the Father's  7'h \nPPO  violation  occurred.  He pled  guilty and\nreceived  45 days  in jail.\nPage  4\nPigors  v Watson  \n2024-001507-DC",
          "source": "8"
        },
        {
          "exhibit_num": 4,
          "bates": "PIGORS-F1-0004",
          "text_preview": "the Court.  He describes\n being  around\nthreaten  him, being  followed  and other  dangerous\nactivities.  These  situations\n are harmful  to the  child  and place  him at risk.\n* \nThe reasonable\n like",
          "source": "13"
        },
        {
          "exhibit_num": 5,
          "bates": "PIGORS-F1-0005",
          "text_preview": "hearing  the argument\n of  the  parties;\nTHE  COURT\n FINDS  AS  FOLLOWS:\n1.  \nOn  February  14, 2025  Plaintiff/Father\n filed  a Motion\n regarding\n Parenting\n Time.\nof  the motion\n included\n the follo",
          "source": "17"
        },
        {
          "exhibit_num": 6,
          "bates": "PIGORS-F1-0006",
          "text_preview": "best interests  of  the child  standard  under  MCL  722.23.  \nThis  request  is based  on\nsignificant\n changes  in circumstances,\n including\n parental  alienation,\n legal  manipulations,\n financial\nf",
          "source": "18"
        },
        {
          "exhibit_num": 7,
          "bates": "PIGORS-F1-0007",
          "text_preview": "IT IS ORDERED\n that  the Plaintiff's\n Motion\n regarding  Parenting\n Tinie  filed  on February  14, 2025  is\ndismissed for the reasons  stated  above. \nParenting  Time  shall  remain  pursuant\n to the ",
          "source": "19"
        },
        {
          "exhibit_num": 8,
          "bates": "PIGORS-F1-0008",
          "text_preview": "IT IS ORDERED,\n unless  otherwise  ordered  in item 11 or 12:\n\u20ac\nStandard  provisions  have  been  modified  (see  item  1l or '12).\n4 : Tho  eihils'ran\n who\n are  gunoortad\n undar\n this\n order  and  t",
          "source": "28"
        },
        {
          "exhibit_num": 9,
          "bates": "PIGORS-F1-0009",
          "text_preview": "hearing.  \n\u20ac  after  statutory  review.  \n\u20ac  on stipulation/consent\n of the parties.\n\u20ac  The friend  of the court  remmmends\n child  support  be ordered  as follows.\n\u20ac \nIf you disagree  with this recom",
          "source": "29"
        },
        {
          "exhibit_num": 10,
          "bates": "PIGORS-F1-0010",
          "text_preview": "defendant.Uninsuredexpensesexoeedingtheannual\nenfo  rmby\"firaae\n blamoundonftThfoer\n oo\"euyrLaaTrhe\"eaynnau'aa:\n ord'o\"ia\"nary\"mediam'a'oatpaindtmth.,in5248fOdTarchol.\nObligation\n Ends.  Except  for c",
          "source": "31"
        },
        {
          "exhibit_num": 11,
          "bates": "PIGORS-F1-0011",
          "text_preview": "HEARING\nEMILY\n WATSON,\nDefendant.\nAndrew\n Pigors\nSelf-Represented\n Litigant\nJennifer\n Batnes  (P55406)\nAttorney\n for  Defendant\nBoth  parties  appeared\n for  a Trial  regarding\n Custody,\n Parenting  T",
          "source": "34"
        },
        {
          "exhibit_num": 12,
          "bates": "PIGORS-F1-0012",
          "text_preview": "hearing  and\nsubpoenaed\n the two health  west  staff  for the next hearing,  which  occurred  on 41/26/25.\nIf a parenting time modification  does not change  the child's  estabfished  \ncustodial\nenvir",
          "source": "39"
        },
        {
          "exhibit_num": 13,
          "bates": "PIGORS-F1-0013",
          "text_preview": "best interests  of the child. It is presumed  to be in the best\ninterests of a child for the child to have a strong  relationship  with both of his or her parents.\nMCL 722.27a(1).  A child has a right",
          "source": "40"
        },
        {
          "exhibit_num": 14,
          "bates": "PIGORS-F1-0014",
          "text_preview": "Judge.  The  Court notes\nthat  the  Father  has been  repeatedly\n warned  of this  behavior  over  the course  of the litigation.\nDespite  numerous\n warnings,  the Father  continues\n to interrupt  the",
          "source": "46"
        },
        {
          "exhibit_num": 15,
          "bates": "PIGORS-F1-0015",
          "text_preview": "hearing  and  subpoenaed\n the two\nheath  west  staff  for  the next  hearing,  which  occurred  on I 1/26/25.  At  that  hearing,  the two\nworks  testified,  the Father  was  about  to provide  testim",
          "source": "49"
        },
        {
          "exhibit_num": 16,
          "bates": "PIGORS-F1-0016",
          "text_preview": "hearing  on the Father's  7'h \nPPO  violation  occurred.  He pled  guilty and\nreceived  45 days  in jail.\nPage  4\nPigors  v Watson\n \n2024-001507-DC",
          "source": "50"
        },
        {
          "exhibit_num": 17,
          "bates": "PIGORS-F1-0017",
          "text_preview": "the Court.  He describes  being  around\nrandom  men who beat him up and threaten  him, being  followed  and other  dangerous\nactivities.  These  situations  are harmful  to the child and place  him at",
          "source": "51"
        },
        {
          "exhibit_num": 18,
          "bates": "PIGORS-F1-0018",
          "text_preview": "ex parte order suspending  his\nparenting  time  is denied.  The  Court  also  notes  that  it offered  supervised\n parenting  time  to the\nFather  and he categorically\n rejected  that.  The  Court  wi",
          "source": "53"
        },
        {
          "exhibit_num": 19,
          "bates": "PIGORS-F1-0019",
          "text_preview": "denied.  The  Court  also  notes  that  it offered  supervised\n parenting  time  to the\nFather  and he categorically\n rejected  that.  The  Court  will consider\n a motion  for  supervised\nparenting  t",
          "source": "54"
        },
        {
          "exhibit_num": 20,
          "bates": "PIGORS-F1-0020",
          "text_preview": "hearings\n and\njail  time,  which\n in  him  caused  job  loss  and  housing\n instability\n that  were\nlater  used  against  me  in custody\n decisions.\nB. Ex Parte Paretxting-Time  Suspension and Lack of",
          "source": "62"
        }
      ]
    },
    "F2": {
      "name": "Fraud on Court",
      "exhibit_count": 20,
      "exhibits": [
        {
          "exhibit_num": 1,
          "bates": "PIGORS-F2-0001",
          "text_preview": "best interests  of  the child  standard  under  MCL  722.23.  \nThis  request  is based  on\nsignificant\n changes  in circumstances,\n including\n parental  alienation,\n legal  manipulations,\n financial\nf",
          "source": "18"
        },
        {
          "exhibit_num": 2,
          "bates": "PIGORS-F2-0002",
          "text_preview": "hearing,  the Plaintiff  stated  that  he was accosted  at the library;  these  same  men were  following\nhim; he could  not say  what  their  names  were;  and stated  that  they  were  arrested.  He",
          "source": "44"
        },
        {
          "exhibit_num": 3,
          "bates": "PIGORS-F2-0003",
          "text_preview": "hearing\n on the  disputed\nallegations\n and  without\n explicit\n findings\n that  I posed  a danger  to Lincoln\nor that  unsupervised\n parenting\n time  was  unsafe.\no  \nThe  continuation\n relied,  at lea",
          "source": "67"
        },
        {
          "exhibit_num": 4,
          "bates": "PIGORS-F2-0004",
          "text_preview": "hearing,  a conclusive\n hearing  had still  not  been  held  by  early  October.\nOn  October  8, 2025,  chambers  finally\n sclieduled\n a \"continuation\"\n of  the matter  for\nOctober  29, 2025-nearly\n t",
          "source": "69"
        },
        {
          "exhibit_num": 5,
          "bates": "PIGORS-F2-0005",
          "text_preview": "Notice\n provisions\n inforining\n tlie  other  party  how  to object;  and\nA  prompt\n hearing\n and  resolution\n of  the  dispute  witliin\n a defined\ntimeframe\n if  an objection\n is filed.\no  \nMichigan\n ",
          "source": "76"
        },
        {
          "exhibit_num": 6,
          "bates": "PIGORS-F2-0006",
          "text_preview": "hearings.\nAppendix\n F -  May  2025  0rders\n Imposing\n Filing\n Bond\n and  Denying\n Post-Judgment\nRelief\nThe  May  16,  2025  order  imposing\n a filing\n bond  requirement.\nThe  May  22, 2025  order  den",
          "source": "82"
        },
        {
          "exhibit_num": 7,
          "bates": "PIGORS-F2-0007",
          "text_preview": "notice,  or that  notice  itself  will  precipitate\n adverse\n action\nbefore  an order  can  be issued.\nWHEREFORE,\n Defendant,  respectfully\n requests\n the  following\nrelieffrom\n this  Honorable\n Court",
          "source": "230"
        },
        {
          "exhibit_num": 8,
          "bates": "PIGORS-F2-0008",
          "text_preview": "due process.\nAuthority:\n MCR  3.207(B);\n MCR  2.11 9; MCR  2.116(C)(8)-(10);\n U.S. Const.  amend.  XIV.\nRelief:  Motion\n must  be vacated  in full.\nII.  PROCEDURAL\n ABUSE  AND  RULE\n VIOLATION\n OBJECT",
          "source": "238"
        },
        {
          "exhibit_num": 9,
          "bates": "PIGORS-F2-0009",
          "text_preview": "hearing\nThat  if  the Court  believes  any  restriction\n on parenting\n time  remains  necessary,  the Court  schedule  a focused\nevidentiary\n hearing  where  both  sides  can present  evidence  and cr",
          "source": "245"
        },
        {
          "exhibit_num": 10,
          "bates": "PIGORS-F2-0010",
          "text_preview": "hearings.\nAppendix\n F -  May  2025  0rders\n Imposing\n Filing\n Bond  and  Denying\n Post-Judgment\nRelief\n*  \nThe  May  16, 2025  order  imposing\n a filing  bond  requirement.\nThe  May  22, 2025  order  ",
          "source": "267"
        },
        {
          "exhibit_num": 11,
          "bates": "PIGORS-F2-0011",
          "text_preview": "Court Rules  and\nFederal Rules of Civil  Procedure, FRCP 26(b)(1),  45(d%3%A) requesting subpoenas issued by Defendant  be quaslied,\nDefendant  be prohibited  from  issuing any further  subpoenas and ",
          "source": "273"
        },
        {
          "exhibit_num": 12,
          "bates": "PIGORS-F2-0012",
          "text_preview": "Dismissed.\n*Tliis  Judgment  is tlie  initial  Order  regarding  the issues  of  Custody  and Parenting\n Time.\n*PlaintiFs\n six (6) Motions  filed  on July  16, 2024,  tlie day  before  Trial,  Denied ",
          "source": "274"
        },
        {
          "exhibit_num": 13,
          "bates": "PIGORS-F2-0013",
          "text_preview": "Court Rules and\nFederal Rules of Civil  Procedure, FRCP 26(b%l),  45(d%3)(A)  requesting subpoenas issued by Defendant  be quaslied,\nDefenday'it be prohibited  from  issuing any fiirtber  subpoenas an",
          "source": "281"
        },
        {
          "exhibit_num": 14,
          "bates": "PIGORS-F2-0014",
          "text_preview": "Dismissed.\n*This  Judgment  is the initial  Order  regarding\n the issues of  Custody  and Parenting\n Time.\n*Plainti'ff's\n six  (6) Motions\n filed  on July  16, 2024,  tlie day  before  Trial,  Denied ",
          "source": "282"
        },
        {
          "exhibit_num": 15,
          "bates": "PIGORS-F2-0015",
          "text_preview": "denied.  He states  that  he believes\n that  as a\nman  he fee's  that  sexism  and  an established\n systemic\n bias  favors  women/mothers\n in regards  to custody\n and  PPO  cases.\nIn order  to respond",
          "source": "287"
        },
        {
          "exhibit_num": 16,
          "bates": "PIGORS-F2-0016",
          "text_preview": "Ex parte shutdown plus financial barrier to filing  for parenting-\ntime reliefj MCR 3.207; MCR 3.310(B); access-to-court concerns; Benchbook \ni Trial: Modify/terminate  ex\nparte;  waive  or relax  bon",
          "source": "354"
        },
        {
          "exhibit_num": 17,
          "bates": "PIGORS-F2-0017",
          "text_preview": "ex parte  communications,\n and  a\nsustained\n pattern  of  favoring\n one  party  over  anotlier\n in  family\n cases\nundermine\n public\n confidence\n in  the  neutrality\n of  the court.\n2. \nCanon\n 2(A)  an",
          "source": "392"
        },
        {
          "exhibit_num": 18,
          "bates": "PIGORS-F2-0018",
          "text_preview": "00.1653 applies to tort actions filed on or after October 1, 1986.\nRule 2.224 Change of Venue in Tort Actions\nCourt",
          "source": "411"
        },
        {
          "exhibit_num": 19,
          "bates": "PIGORS-F2-0019",
          "text_preview": "rofessional authority:\n1. Fabrication of Evidence\nOctober 15, 2023: Emily alleged that she discovered a straw with s",
          "source": "444"
        },
        {
          "exhibit_num": 20,
          "bates": "PIGORS-F2-0020",
          "text_preview": "r periods of alienation or hostility.\nExample: On November 15, 2024, after being withheld for 25 days, LDW demonstrat",
          "source": "655"
        }
      ]
    },
    "F3": {
      "name": "Judicial Disqualification",
      "exhibit_count": 20,
      "exhibits": [
        {
          "exhibit_num": 1,
          "bates": "PIGORS-F3-0001",
          "text_preview": "HEARING\n 11/26/2025\nEMILY  A. WATSON,\nDefendant\nDefendant\n requested,\n and  the Court  signed  an ex parte  order  suspending\n the  Plaintiff's\nparenting  time.  An evidentiary\n hearing  was held on S",
          "source": "1"
        },
        {
          "exhibit_num": 2,
          "bates": "PIGORS-F3-0002",
          "text_preview": "HEARING  11/26/2025\nEMILY  A. WATSON,\nDefendant\nDefendant  requested,  and the Court  signed  an ex parte  order  suspending  the Plaintiffs\nparenting  time. An evidentiary  hearing  was held on Septe",
          "source": "37"
        },
        {
          "exhibit_num": 3,
          "bates": "PIGORS-F3-0003",
          "text_preview": "ex parte order suspending  his\nparenting  time  is denied.  The  Court  also  notes  that  it offered  supervised\n parenting  time  to the\nFather  and he categorically\n rejected  that.  The  Court  wi",
          "source": "53"
        },
        {
          "exhibit_num": 4,
          "bates": "PIGORS-F3-0004",
          "text_preview": "hearing\n on October\n 29, 2025.\n2.  \nLack\n of  notice\n and  ambush\n at a scheduled\n parenting-time\n exchange.\no  \nI was  not  served  with  the  ex parte  motion\n or order  before  an August\n 8,\n2025  ",
          "source": "58"
        },
        {
          "exhibit_num": 5,
          "bates": "PIGORS-F3-0005",
          "text_preview": "hearings\n and\njail  time,  which\n in  him  caused  job  loss  and  housing\n instability\n that  were\nlater  used  against  me  in custody\n decisions.\nB. Ex Parte Paretxting-Time  Suspension and Lack of",
          "source": "62"
        },
        {
          "exhibit_num": 6,
          "bates": "PIGORS-F3-0006",
          "text_preview": "notice\n of\nSuSpenSlOn.\no  \nI was  not  served  with  the  ex parte  motion\n or order  before  the  August\n 8\nscheduled\n exchange.\no  \nI arrived\n expecting\n my  regular\n parenting\n time.  Emily\n did  n",
          "source": "64"
        },
        {
          "exhibit_num": 7,
          "bates": "PIGORS-F3-0007",
          "text_preview": "hearings.\n(Micl'iigan\n Courts)\no  \nMCR  3.207(B)(1)\n and  (B)(5)-(6)\n govern\n ex parte  custody\n and  parenting-\ntime  orders  and  require:\nSpecific\n facts  in a verified\n pleading\n or affidavit\n sli",
          "source": "75"
        },
        {
          "exhibit_num": 8,
          "bates": "PIGORS-F3-0008",
          "text_preview": "hearing.\nAppendix\n E -  Ex  Parte  and  Post-Ex\n Parte  Orders\n in  August-October\n 2025\nThe  ex parte  order  suspending\n all  parenting\n time  (entered\n 011 or about  August\n 6,\n2025).\nSubsequent\n o",
          "source": "81"
        },
        {
          "exhibit_num": 9,
          "bates": "PIGORS-F3-0009",
          "text_preview": "hearing or if more than 14 days have passed since  the ex parte  order  was served.\noFo%at'::J21)25\n \nau'&A4oug{;J\"t\"\"\"\nApproved,  SCAO\nForm  CC 379, Rev. 3/23\nMCL  600.2950,  MCL  600.2950a,  MCR 3.7",
          "source": "229"
        },
        {
          "exhibit_num": 10,
          "bates": "PIGORS-F3-0010",
          "text_preview": "EX PARTE  MOTION  TO  SUSPEND\n PLAINTIFF'S\nPARENTING\n TIME\nAt a session  of said  Court,  held  in the\nCourthouse  in the Counjy  of Muskegon,  State of Michigan\nPresent  Hon. JENNY  L MCNEILL\nWHEREAS",
          "source": "231"
        },
        {
          "exhibit_num": 11,
          "bates": "PIGORS-F3-0011",
          "text_preview": "hearing  with  the  court.\n3. \nThe  ex parte  order  will automatically\n become  a temporary\n order  if you  do not  file a written\nobjection\n or motion  to modify  or rescind  the  ex parte  order  a",
          "source": "233"
        },
        {
          "exhibit_num": 12,
          "bates": "PIGORS-F3-0012",
          "text_preview": "hearing.\nEVen !f an ObjeCt!On !S f!!ed, Fle eX parte OrCier !V!11 rema!n In effeCk and mLlSi 5e Obeied\nunless  changed\n by a later  court  order.",
          "source": "234"
        },
        {
          "exhibit_num": 13,
          "bates": "PIGORS-F3-0013",
          "text_preview": "Ex Parte Motion iuccor4a<<e\nwith Michigan  Court Rules. This marks at least the fourth  instance of  evasion de6gned :\nsuppress Plaintiffs  ability  to receive notice, present rebuttal, or obtain time",
          "source": "235"
        },
        {
          "exhibit_num": 14,
          "bates": "PIGORS-F3-0014",
          "text_preview": "hearing.\nThe August  ex parte  order  did not simply  adjust  one exchange;  it completely\n stopped  my  parenting  time  and erased\nupcoming  holiday  and special-event\n time,  including  Labor  Day ",
          "source": "243"
        },
        {
          "exhibit_num": 15,
          "bates": "PIGORS-F3-0015",
          "text_preview": "hearing;  require  specific\n danger\nfindings.\n9 i Lincoln's 3rd birthday in 2025 (under suspension)i 3rd birthday missed during ongoing ex parte-based\nshutdown \ni MCL 722.27a(3); birthday/special-even",
          "source": "247"
        },
        {
          "exhibit_num": 16,
          "bates": "PIGORS-F3-0016",
          "text_preview": "hearing\n on October\n 29, 2025.\n2. \nLack  of  notice\n and  ambush\n at a scheduled\n parenting-time\n exchange.\no  \nI was  not  served  with  the  ex parte  motion\n or order  before  an August\n 8,\n2025  e",
          "source": "251"
        },
        {
          "exhibit_num": 17,
          "bates": "PIGORS-F3-0017",
          "text_preview": "hearings\n and\njail  time,  which\n in  turn  caused  job  loss  and  housing\n instability\n that  were\nlater  used  against  me  in custody\n decisions.\nE. Ex Parte Paretxting-Time  Suspeiision and Lack ",
          "source": "255"
        },
        {
          "exhibit_num": 18,
          "bates": "PIGORS-F3-0018",
          "text_preview": "hearings.\n(Michigan\n Courts)\no  \nMCR  3.207(B)(1)\n and  (B)(5)-(6)\n govern\n ex parte  custody\n and  parenting-\ntime  orders  and  require:\nSpecific\n facts  in a verified\n pleading\n or affidavit\n showi",
          "source": "263"
        },
        {
          "exhibit_num": 19,
          "bates": "PIGORS-F3-0019",
          "text_preview": "denied.  He states  that  he believes\n that  as a\nman  he fee's  that  sexism  and  an established\n systemic\n bias  favors  women/mothers\n in regards  to custody\n and  PPO  cases.\nIn order  to respond",
          "source": "287"
        },
        {
          "exhibit_num": 20,
          "bates": "PIGORS-F3-0020",
          "text_preview": "EX PARTE MOTION  TO SUSPEND  PLAINTIFF'S\n PARENTING  TIME\nNOW  COMES  Defendant,\n EmilyWatson,\n files  the  Emergency\n Ex Parte  Motion  to Suspend\nParenting\n Time,  station  as follows:\nq, \nTheDefend",
          "source": "339"
        }
      ]
    },
    "F4": {
      "name": "\u00a71983 Federal Complaint",
      "exhibit_count": 20,
      "exhibits": [
        {
          "exhibit_num": 1,
          "bates": "PIGORS-F4-0001",
          "text_preview": "due process.\nAuthority:\n MCR  3.207(B);\n MCR  2.11 9; MCR  2.116(C)(8)-(10);\n U.S. Const.  amend.  XIV.\nRelief:  Motion\n must  be vacated  in full.\nII.  PROCEDURAL\n ABUSE  AND  RULE\n VIOLATION\n OBJECT",
          "source": "238"
        },
        {
          "exhibit_num": 2,
          "bates": "PIGORS-F4-0002",
          "text_preview": "notice, present rebuttal, or obtain timely  relM.  \n;3'i\nThis  defect  is not  clerical-it\n is a systematic\n abuse  of  the judicial\n process  to deny  access  to the\nforum  and obstruct  due process.",
          "source": "239"
        },
        {
          "exhibit_num": 3,
          "bates": "PIGORS-F4-0003",
          "text_preview": "due process);  Canon/JTC\n narrative\n on pattern  of  treatment.",
          "source": "355"
        },
        {
          "exhibit_num": 4,
          "bates": "PIGORS-F4-0004",
          "text_preview": "Granville standard\n\u2022 Irreparable harm\n\u2022 Damages: $50,000-100,000\nCount 2: Due Process Violation (Right to",
          "source": "2055"
        },
        {
          "exhibit_num": 5,
          "bates": "PIGORS-F4-0005",
          "text_preview": "pired to deprive constitutional rights\n\u2022 Damages: $50,000-100,000\nTotal Potential Damages: $200,000-400,000",
          "source": "2060"
        },
        {
          "exhibit_num": 6,
          "bates": "PIGORS-F4-0006",
          "text_preview": "comprehensive federal civil rights action seeking $200,000-\n400,000 in damages plus attorney fees. However,",
          "source": "2064"
        },
        {
          "exhibit_num": 7,
          "bates": "PIGORS-F4-0007",
          "text_preview": "ski v Bednarksi, 141 Mich App 15,\n21 (1985).\n35On February 22, 2016, the Michigan Department of Civil Rights (MDCR)\u2014D",
          "source": "2243"
        },
        {
          "exhibit_num": 8,
          "bates": "PIGORS-F4-0008",
          "text_preview": "tation statute, MCL 722.27b,\nunconstitutional. On March 28, 2002, the lower court found the\ndefendant in Johnson i",
          "source": "2540"
        },
        {
          "exhibit_num": 9,
          "bates": "PIGORS-F4-0009",
          "text_preview": "NG_TIME|dates=DATE_M\nDY:10/8/2025|DATE_MONTH_DY_Y:June 13, 2025|snip=, due process \\n**Source:** 0719T04:30, moti",
          "source": "11664"
        },
        {
          "exhibit_num": 10,
          "bates": "PIGORS-F4-0010",
          "text_preview": "ry Stack (Machine Grammar)\npage 22\nATE_MONTH_DY_Y:August 22, 2025|snip=runs afoul of due process (14th Amendment) a",
          "source": "11671"
        },
        {
          "exhibit_num": 11,
          "bates": "PIGORS-F4-0011",
          "text_preview": "|HEALTHWEST|PARENTING_TIME|dates=DATE_MO\nNTH_DY_Y:August 22, 2025|snip=runs afoul of due process (14th Amendment) a",
          "source": "11672"
        },
        {
          "exhibit_num": 12,
          "bates": "PIGORS-F4-0012",
          "text_preview": "C|HEALTHWEST|PARENTING_TIME|dates=DATE_MONTH_DY_Y:August 22, 2025|snip=r\nuns afoul of due process (14th Amendment)",
          "source": "11673"
        },
        {
          "exhibit_num": 13,
          "bates": "PIGORS-F4-0013",
          "text_preview": "the outcome\nwas preordained without due process.\nSeptember 19, 2025 \u2013 Five Parenting-Time Periods Missed (Ongoing Har",
          "source": "29596"
        },
        {
          "exhibit_num": 14,
          "bates": "PIGORS-F4-0014",
          "text_preview": "actions, Plaintiff would not have been evicted on July\n10, 2025. Had due process been afforded, one of two outcom",
          "source": "30035"
        },
        {
          "exhibit_num": 15,
          "bates": "PIGORS-F4-0015",
          "text_preview": "0\nEmotional distress\nSevere trauma, child present\n$50,000\u2013$100,000\n\u00a71983 civil rights violation\nUnlawful se",
          "source": "33798"
        },
        {
          "exhibit_num": 16,
          "bates": "PIGORS-F4-0016",
          "text_preview": "nal distress\nSevere trauma, child present\n$50,000\u2013$100,000\n\u00a71983 civil rights violation\nUnlawful seizure, of",
          "source": "33799"
        },
        {
          "exhibit_num": 17,
          "bates": "PIGORS-F4-0017",
          "text_preview": "lay groundwork for the due process argument.\n\u201cOn April 14, 2025, a bench trial started but was adjourned to April",
          "source": "33844"
        },
        {
          "exhibit_num": 18,
          "bates": "PIGORS-F4-0018",
          "text_preview": "sion Harm\n$250 fee block + cost of forced motions\n$500\u2013\n$1,000\nx2\n$1,000\u2013$2,000\n8. Constitutional Harm\n\u00a7",
          "source": "33891"
        },
        {
          "exhibit_num": 19,
          "bates": "PIGORS-F4-0019",
          "text_preview": "arm\n$250 fee block + cost of forced motions\n$500\u2013\n$1,000\nx2\n$1,000\u2013$2,000\n8. Constitutional Harm\n\u00a71983 civ",
          "source": "33892"
        },
        {
          "exhibit_num": 20,
          "bates": "PIGORS-F4-0020",
          "text_preview": "ee block + cost of forced motions\n$500\u2013\n$1,000\nx2\n$1,000\u2013$2,000\n8. Constitutional Harm\n\u00a71983 civil rights",
          "source": "33893"
        }
      ]
    },
    "F5": {
      "name": "MSC Superintending Control",
      "exhibit_count": 20,
      "exhibits": [
        {
          "exhibit_num": 1,
          "bates": "PIGORS-F5-0001",
          "text_preview": "the court.\n2. \nCanon\n 2(A)  and  2(B)  -  Avoiding\n impropriety\n and  the  appearance\n of\nimpropriety;\n equal  treatment.\n ()\no  \nCanon  2(A)  reqriires\n judges\n to avoid  both  impropriety\n and  the\n",
          "source": "74"
        },
        {
          "exhibit_num": 2,
          "bates": "PIGORS-F5-0002",
          "text_preview": "Lincoln during Andrew\u2019s scheduled parenting time.\nOctober 25, 2024: Emily avoids mediation, forcing custody disputes",
          "source": "483"
        },
        {
          "exhibit_num": 3,
          "bates": "PIGORS-F5-0003",
          "text_preview": "arenting class, avoiding\ncollaborative solutions.\nSeptember 8, 2024: Andrew observes regression in Lincoln\u2019s behavior",
          "source": "496"
        },
        {
          "exhibit_num": 4,
          "bates": "PIGORS-F5-0004",
          "text_preview": "court may have lacked jurisdiction to modify the July 17, 2024 custody order \nbecause:\n\u2022 The modification was ba",
          "source": "2052"
        },
        {
          "exhibit_num": 5,
          "bates": "PIGORS-F5-0005",
          "text_preview": "\u2022 Void all custody modification orders\n\u2022 Restore July 17, 2024 custody order\n\u2022 Award attorney fees and costs\nStr",
          "source": "2053"
        },
        {
          "exhibit_num": 6,
          "bates": "PIGORS-F5-0006",
          "text_preview": "ge: The Honorable Jenny L. McNeill\nDate of Brief: February 11, 2026\nTABLE OF CONTENTS\nI. STATEMENT OF JURISDICTION\nII",
          "source": "2066"
        },
        {
          "exhibit_num": 7,
          "bates": "PIGORS-F5-0007",
          "text_preview": "Supreme Court filing fee exists in statute (e.g., $375). Michigan Legislature\nBehavior: docketing/proces",
          "source": "2218"
        },
        {
          "exhibit_num": 8,
          "bates": "PIGORS-F5-0008",
          "text_preview": "has the following jurisdiction:\n\u2022\nCivil claims of $25,000 or less. MCL 600.8301(1).\n\u2022 \u201c[I]n its subject-mat",
          "source": "2244"
        },
        {
          "exhibit_num": 9,
          "bates": "PIGORS-F5-0009",
          "text_preview": "leadings, even if a\nplaintiff\u2019s proofs exceed the $25,000 jurisdictional limit\nof the district court under",
          "source": "2245"
        },
        {
          "exhibit_num": 10,
          "bates": "PIGORS-F5-0010",
          "text_preview": "e or she is limited\nto the jurisdictional amount ($25,000)).\n\u2022 \u201cA joint stipulation in good faith to an amo",
          "source": "2247"
        },
        {
          "exhibit_num": 11,
          "bates": "PIGORS-F5-0011",
          "text_preview": "e family division\nof the circuit court, effective January 1, 1998.\nA. Concurrent Jurisdiction\n\u201cIn addition to the j",
          "source": "2263"
        },
        {
          "exhibit_num": 12,
          "bates": "PIGORS-F5-0012",
          "text_preview": ", approved by the\nsupreme court, and in effect on December 31, 2012, is considered valid\nand in compliance with the r",
          "source": "2264"
        },
        {
          "exhibit_num": 13,
          "bates": "PIGORS-F5-0013",
          "text_preview": "c filing system means \u201ca system authorized after\n[January 1, 20162] by the supreme court for the electronic filing",
          "source": "2318"
        },
        {
          "exhibit_num": 14,
          "bates": "PIGORS-F5-0014",
          "text_preview": "nship PPO)\nPrepared by: Legal Analysis Team\nDate: February 10, 2026\nJurisdiction: 14th Judicial Circuit Court, Muskeg",
          "source": "2463"
        },
        {
          "exhibit_num": 15,
          "bates": "PIGORS-F5-0015",
          "text_preview": "seeking of employment as that authority exists on\nAugust 10, 1998.\n(f) If available within the court\u2019s jurisdiction",
          "source": "2531"
        },
        {
          "exhibit_num": 16,
          "bates": "PIGORS-F5-0016",
          "text_preview": "seeking of employment\nas that authority exists on August 10, 1998.\n(f) If available within the court\u2019s jurisdiction",
          "source": "2548"
        },
        {
          "exhibit_num": 17,
          "bates": "PIGORS-F5-0017",
          "text_preview": "ing a contempt\norder where the defendant paid the $1,000 to avoid confinement,\nand the defendant\u2019s counsel",
          "source": "2552"
        },
        {
          "exhibit_num": 18,
          "bates": "PIGORS-F5-0018",
          "text_preview": "m) (White (Kadeem) I), 493 Mich 187 (2013).\n13 On April 12, 2013, the Michigan Supreme Court issued similar orders",
          "source": "2680"
        },
        {
          "exhibit_num": 19,
          "bates": "PIGORS-F5-0019",
          "text_preview": "(Custody), 2023-5907-PP (PPO)\nDate of Complaint: February 11, 2026\nI. INTRODUCTION AND JURISDICTION\nThis formal comp",
          "source": "3709"
        },
        {
          "exhibit_num": 20,
          "bates": "PIGORS-F5-0020",
          "text_preview": "Special Proceedings and Actions Page 351 Updated September\n1, 2025\nNode: R339 | Title: exclusive jurisdiction as def",
          "source": "5655"
        }
      ]
    },
    "F6": {
      "name": "JTC Complaint",
      "exhibit_count": 20,
      "exhibits": [
        {
          "exhibit_num": 1,
          "bates": "PIGORS-F6-0001",
          "text_preview": "the court.\n2. \nCanon\n 2(A)  and  2(B)  -  Avoiding\n impropriety\n and  the  appearance\n of\nimpropriety;\n equal  treatment.\n ()\no  \nCanon  2(A)  reqriires\n judges\n to avoid  both  impropriety\n and  the\n",
          "source": "74"
        },
        {
          "exhibit_num": 2,
          "bates": "PIGORS-F6-0002",
          "text_preview": "hearing\n occurred,\n despite\n my  objection\n and  repeated\n requests,\nand  without\n detailed\n best-interest\n findings\n during\n the  extended\n suspension.\n5. \nCanon\n 3(A)(3)\n -  Patience,\n dignity,\n and",
          "source": "78"
        },
        {
          "exhibit_num": 3,
          "bates": "PIGORS-F6-0003",
          "text_preview": "due process);  Canon/JTC\n narrative\n on pattern  of  treatment.",
          "source": "355"
        },
        {
          "exhibit_num": 4,
          "bates": "PIGORS-F6-0004",
          "text_preview": "ex parte\ncommunications,\n fair  opportunity\n to be heard).  (Michigan\n Courts)\nII.  SUMMARY\n OF  MISCONDUCT\nDrawing\n on my  compiled\n narrative,\n timeline,\n and  my  record,  the core  patteriis\n I ha",
          "source": "375"
        },
        {
          "exhibit_num": 5,
          "bates": "PIGORS-F6-0005",
          "text_preview": "ex parte,  contraiy\n to the  prohibition\n on ex parte\ncommunications\n about  pending\n matters  in Canon  3(A)(5)\n and  the\nrequirement\n that  judicial\n decisions\n be based  on evidence\n properly\n in  ",
          "source": "388"
        },
        {
          "exhibit_num": 6,
          "bates": "PIGORS-F6-0006",
          "text_preview": "ex parte  communications,\n and  a\nsustained\n pattern  of  favoring\n one  party  over  anotlier\n in  family\n cases\nundermine\n public\n confidence\n in  the  neutrality\n of  the court.\n2. \nCanon\n 2(A)  an",
          "source": "392"
        },
        {
          "exhibit_num": 7,
          "bates": "PIGORS-F6-0007",
          "text_preview": "ex parte\ncommunications.\n (Michizan  Courts)\no  \nCanon  3 requires\n that  a judge  perfon'n\n judicial\n duties  impartially\n and\ndiligently,\n and  bars  ex parte  communications\n on the  merits  of  pe",
          "source": "394"
        },
        {
          "exhibit_num": 8,
          "bates": "PIGORS-F6-0008",
          "text_preview": "ex parte  evidence\n handling\n inconsistent\n with  Canon\n3 and  with  the  requirement\n that  decisions\n be based  on the  record.\n4.  \nMCR\n 3.207  and  related\n authorities\n governing\n ex parte  order",
          "source": "395"
        },
        {
          "exhibit_num": 9,
          "bates": "PIGORS-F6-0009",
          "text_preview": "TION\n OF MISCONDUCT\".\nThe Time]ine  begins  with  May  15, 2023 (a]ready  heard by this  Court),  continues  thro",
          "source": "2739"
        },
        {
          "exhibit_num": 10,
          "bates": "PIGORS-F6-0010",
          "text_preview": "TION\n OF MISCONDUCT\".\nThe Timeline  begins  with  May  15, 2023 (already  heard by this  Court),  continues  thro",
          "source": "2820"
        },
        {
          "exhibit_num": 11,
          "bates": "PIGORS-F6-0011",
          "text_preview": "See State Bar of Michigan Ethics Opinion, JI-66 (March 23, 1993),\nregarding a judge\u2019s participation on the board",
          "source": "3227"
        },
        {
          "exhibit_num": 12,
          "bates": "PIGORS-F6-0012",
          "text_preview": "_________\nPrinted Name: Andrew James Pigors\nDate: February 11, 2026\nAPPENDIX A: MICHIGAN CODE OF JUDICIAL CONDUCT \nVI",
          "source": "3727"
        },
        {
          "exhibit_num": 13,
          "bates": "PIGORS-F6-0013",
          "text_preview": "n| 4 | **Suppressed evidence at custody trial** | July 17, 2024 | MCR 2.401, MCR 2.507(G), \nCanon 3(B)(7) | Tier",
          "source": "3729"
        },
        {
          "exhibit_num": 14,
          "bates": "PIGORS-F6-0014",
          "text_preview": "5-002760-CZ**  \\nBasis: Verified Complaint (Filed June 12, 2025) + TRO Denial (June 18, 2025) + Canon Pattern\\n\\n",
          "source": "3810"
        },
        {
          "exhibit_num": 15,
          "bates": "PIGORS-F6-0015",
          "text_preview": "ied Complaint (Filed June 12, 2025) + TRO Denial (June 18, 2025) + Canon Pattern\\n\\n---\n\\n\\n## \\ud83c\\udfaf STRAT",
          "source": "3811"
        },
        {
          "exhibit_num": 16,
          "bates": "PIGORS-F6-0016",
          "text_preview": "n:123\nregister of actions:68\nreturn of service:57\n$250:55\nmittimus:49\nrecusal:34\nfiling bond:25\nTOP_CASE",
          "source": "3978"
        },
        {
          "exhibit_num": 17,
          "bates": "PIGORS-F6-0017",
          "text_preview": "nal contempt|jail\nMEEK4=bias|recusal|disqual|bond/$250|sanction|JTC|HealthWest eval reliance\nMEEK1=housi",
          "source": "3979"
        },
        {
          "exhibit_num": 18,
          "bates": "PIGORS-F6-0018",
          "text_preview": "dge.\u201d State\nBar of Michigan Ethics Opinion, JI-8 (July 19, 1989).\n2 Written ethics opinions are accessible on the",
          "source": "4290"
        },
        {
          "exhibit_num": 19,
          "bates": "PIGORS-F6-0019",
          "text_preview": "ted.\u201d State Bar of Michigan\nEthics Opinion, JI-8 (July 19, 1989).\nC.\nWho May Raise the Issue of Disqualification",
          "source": "4291"
        },
        {
          "exhibit_num": 20,
          "bates": "PIGORS-F6-0020",
          "text_preview": ". See State Bar\nof Michigan Ethics Opinion JI-34 (December 21, 1990), for more detailed information. \n5Note: disquali",
          "source": "4292"
        }
      ]
    },
    "F7": {
      "name": "Custody Modification",
      "exhibit_count": 20,
      "exhibits": [
        {
          "exhibit_num": 1,
          "bates": "PIGORS-F7-0001",
          "text_preview": "HEARING\n 11/26/2025\nEMILY  A. WATSON,\nDefendant\nDefendant\n requested,\n and  the Court  signed  an ex parte  order  suspending\n the  Plaintiff's\nparenting  time.  An evidentiary\n hearing  was held on S",
          "source": "1"
        },
        {
          "exhibit_num": 2,
          "bates": "PIGORS-F7-0002",
          "text_preview": "hearing  and\nsubpoenaed\n the  \nwhich  occurred  on 1 1/26/25.\nLaw\nIf a \nparenting  \ntime \nmodification\n \ndoes  not change  the \nchild's  \nestablished\n \ncustodial\nenvironment,\n the parenting  time  mod",
          "source": "3"
        },
        {
          "exhibit_num": 3,
          "bates": "PIGORS-F7-0003",
          "text_preview": "notice  when  parenting  time  wifl not occur.\n(i) Any  other  reasonable\n condition  determined\n to be appropriate\n in the particular case. MCL\n722.27a(9).\nPage 2\nPigors  v Watson  \n2024-001507-DC",
          "source": "4"
        },
        {
          "exhibit_num": 4,
          "bates": "PIGORS-F7-0004",
          "text_preview": "the Court.  He describes\n being  around\nthreaten  him, being  followed  and other  dangerous\nactivities.  These  situations\n are harmful  to the  child  and place  him at risk.\n* \nThe reasonable\n like",
          "source": "13"
        },
        {
          "exhibit_num": 5,
          "bates": "PIGORS-F7-0005",
          "text_preview": "hearing  the argument\n of  the  parties;\nTHE  COURT\n FINDS  AS  FOLLOWS:\n1.  \nOn  February  14, 2025  Plaintiff/Father\n filed  a Motion\n regarding\n Parenting\n Time.\nof  the motion\n included\n the follo",
          "source": "17"
        },
        {
          "exhibit_num": 6,
          "bates": "PIGORS-F7-0006",
          "text_preview": "best interests  of  the child  standard  under  MCL  722.23.  \nThis  request  is based  on\nsignificant\n changes  in circumstances,\n including\n parental  alienation,\n legal  manipulations,\n financial\nf",
          "source": "18"
        },
        {
          "exhibit_num": 7,
          "bates": "PIGORS-F7-0007",
          "text_preview": "IT IS ORDERED\n that  the Plaintiff's\n Motion\n regarding  Parenting\n Tinie  filed  on February  14, 2025  is\ndismissed for the reasons  stated  above. \nParenting  Time  shall  remain  pursuant\n to the ",
          "source": "19"
        },
        {
          "exhibit_num": 8,
          "bates": "PIGORS-F7-0008",
          "text_preview": "hearing.  Nothing  in Plaintiff's  Motion\nindicates  a change  of  circumstances\n as required  by law.\n3. \nPlaintiff\n makes  numerous  allegations,\n which  the Family  Court  Specialist\n addressed.  T",
          "source": "20"
        },
        {
          "exhibit_num": 9,
          "bates": "PIGORS-F7-0009",
          "text_preview": "hearing,  the Plaintiff\n addressed  the  fact  that  the Mother  had  her Easter  weekend,  which  fell  on his\nweekend.  He demanded  make-up  parenting\n time  (The  Plaintiff\n also tried  to file  a",
          "source": "21"
        },
        {
          "exhibit_num": 10,
          "bates": "PIGORS-F7-0010",
          "text_preview": "NOTICE\n REQUIREMENTS\nEach party shall immediately\n notify  the Office  of  Fatnily  Court  Services,  in  writing,\n of  any  changes  in\ntheir mailing  address, resiaence address, email  address  and ",
          "source": "22"
        },
        {
          "exhibit_num": 11,
          "bates": "PIGORS-F7-0011",
          "text_preview": "HEARING\nEMILY\n WATSON,\nDefendant.\nAndrew\n Pigors\nSelf-Represented\n Litigant\nJennifer\n Batnes  (P55406)\nAttorney\n for  Defendant\nBoth  parties  appeared\n for  a Trial  regarding\n Custody,\n Parenting  T",
          "source": "34"
        },
        {
          "exhibit_num": 12,
          "bates": "PIGORS-F7-0012",
          "text_preview": "hearing\n was  held;  and  the  Court  rendered\n an oral  opinion.\n The  Defendant  submitted  an order\nunder  the 7 day  rule,  using  parts  of  the  rulings\n the  Court  made  regarding\n the  best i",
          "source": "35"
        },
        {
          "exhibit_num": 13,
          "bates": "PIGORS-F7-0013",
          "text_preview": "best interest  factors;  the\nPlaintiff\n filed  an objection,\n but  failed\n to follow\n the  Court  rules,  in  stating  with  specificity\n what  parts of\nthe  order  he objected\n to and  did  not  prov",
          "source": "36"
        },
        {
          "exhibit_num": 14,
          "bates": "PIGORS-F7-0014",
          "text_preview": "HEARING  11/26/2025\nEMILY  A. WATSON,\nDefendant\nDefendant  requested,  and the Court  signed  an ex parte  order  suspending  the Plaintiffs\nparenting  time. An evidentiary  hearing  was held on Septe",
          "source": "37"
        },
        {
          "exhibit_num": 15,
          "bates": "PIGORS-F7-0015",
          "text_preview": "hearing  and\nsubpoenaed\n the two health  west  staff  for the next hearing,  which  occurred  on 41/26/25.\nIf a parenting time modification  does not change  the child's  estabfished  \ncustodial\nenvir",
          "source": "39"
        },
        {
          "exhibit_num": 16,
          "bates": "PIGORS-F7-0016",
          "text_preview": "best interests  of the child. It is presumed  to be in the best\ninterests of a child for the child to have a strong  relationship  with both of his or her parents.\nMCL 722.27a(1).  A child has a right",
          "source": "40"
        },
        {
          "exhibit_num": 17,
          "bates": "PIGORS-F7-0017",
          "text_preview": "notice  when  parenting  time  will not occur.\n(i) Any  other  reasonable\n condition  determined\n to be appropriate\n in the particular case. MCL\n722.27a(9).\nPage 2\nPigors  v Watson  \n2024-001507-DC",
          "source": "41"
        },
        {
          "exhibit_num": 18,
          "bates": "PIGORS-F7-0018",
          "text_preview": "the Court.  He describes  being  around\nrandom  men who beat him up and threaten  him, being  followed  and other  dangerous\nactivities.  These  situations  are harmful  to the child and place  him at",
          "source": "51"
        },
        {
          "exhibit_num": 19,
          "bates": "PIGORS-F7-0019",
          "text_preview": "ex parte order suspending  his\nparenting  time  is denied.  The  Court  also  notes  that  it offered  supervised\n parenting  time  to the\nFather  and he categorically\n rejected  that.  The  Court  wi",
          "source": "53"
        },
        {
          "exhibit_num": 20,
          "bates": "PIGORS-F7-0020",
          "text_preview": "denied.  The  Court  also  notes  that  it offered  supervised\n parenting  time  to the\nFather  and he categorically\n rejected  that.  The  Court  will consider\n a motion  for  supervised\nparenting  t",
          "source": "54"
        }
      ]
    },
    "F8": {
      "name": "COA Leave Application",
      "exhibit_count": 20,
      "exhibits": [
        {
          "exhibit_num": 1,
          "bates": "PIGORS-F8-0001",
          "text_preview": "hearing\n and  address  the  child's\nbest  interests\n within\n a reasonable\n time,  and  that  failure\n to comply\n with\nMCR  3.207's\n notice  and  heating\n requirements\n is error.  (FindLaw\n Case\nLaw)\no",
          "source": "77"
        },
        {
          "exhibit_num": 2,
          "bates": "PIGORS-F8-0002",
          "text_preview": "ex parte  order  or to restore  parenting  time.  When  you\ncombine  that financial  barrier  with  the ex parte shutdown,  it leaves  my  son without  his father  and leaves me with  no\nrealistic  wr",
          "source": "348"
        },
        {
          "exhibit_num": 3,
          "bates": "PIGORS-F8-0003",
          "text_preview": "Lincoln to trick-or-treat together on Halloween.\nOctober 30, 2024: Emily leaves for vacation early, taking Lincoln",
          "source": "481"
        },
        {
          "exhibit_num": 4,
          "bates": "PIGORS-F8-0004",
          "text_preview": "extended withholding periods, such as March 26 to May 2, 2024, LDW displayed\nreluctance to leave my care, sugge",
          "source": "652"
        },
        {
          "exhibit_num": 5,
          "bates": "PIGORS-F8-0005",
          "text_preview": "order that is the subject of this appeal.\nB. The August 5, 2025 Ex Parte Suspension Order\nOn August 5, 2025, Fath",
          "source": "2070"
        },
        {
          "exhibit_num": 6,
          "bates": "PIGORS-F8-0006",
          "text_preview": "appeals/applications/original proceedings (e.g., $375). Michigan Legislature\nPrinted using ChatGPT to P",
          "source": "2217"
        },
        {
          "exhibit_num": 7,
          "bates": "PIGORS-F8-0007",
          "text_preview": "cision of the Court of Appeals issued on or after November 1,\n1990, that has not been reversed or modified by the Su",
          "source": "2232"
        },
        {
          "exhibit_num": 8,
          "bates": "PIGORS-F8-0008",
          "text_preview": "cision of the Court of Appeals issued on or after November 1, 1990, that has\nnot been reversed or modified by the Su",
          "source": "2498"
        },
        {
          "exhibit_num": 9,
          "bates": "PIGORS-F8-0009",
          "text_preview": "er curiam opinion of\nthe Court of Appeals, issued October 28, 2008 (Docket No. 278470).",
          "source": "2499"
        },
        {
          "exhibit_num": 10,
          "bates": "PIGORS-F8-0010",
          "text_preview": "er curiam opinion\nof the Court of Appeals, issued October 28, 2008 (Docket\nNo. 278470).\nD.\nFines Must Generally be P",
          "source": "2527"
        },
        {
          "exhibit_num": 11,
          "bates": "PIGORS-F8-0011",
          "text_preview": "ing his\nchildren to another state. Id. at 335. On January 25, 2002, the Court of\nAppeals issued its decision in DeRo",
          "source": "2539"
        },
        {
          "exhibit_num": 12,
          "bates": "PIGORS-F8-0012",
          "text_preview": "han 90 days and may fine the person not more\nthan $500. MCL 764.15f(1)(e).\n64\u201c[A] prior Court of Appeals",
          "source": "2557"
        },
        {
          "exhibit_num": 13,
          "bates": "PIGORS-F8-0013",
          "text_preview": "r curiam opinion of the Court of Appeals, \nissued October 28, 2008 (Docket No. 278470) 4-8\nEx parte Terry, 128 US 28",
          "source": "2560"
        },
        {
          "exhibit_num": 14,
          "bates": "PIGORS-F8-0014",
          "text_preview": "cision of the Court of Appeals issued on or after November 1, \n1990, that has not been reversed or modified by the Su",
          "source": "2632"
        },
        {
          "exhibit_num": 15,
          "bates": "PIGORS-F8-0015",
          "text_preview": "er curiam opinion of the Court of Appeals, issued March 12, 2015\n(Docket No. 323246)10 (finding that the trial cou",
          "source": "2651"
        },
        {
          "exhibit_num": 16,
          "bates": "PIGORS-F8-0016",
          "text_preview": "er\ncuriam opinion of the Court of Appeals, issued March 12, 2015\n24 See also Section 2.2(C) (presence of controlle",
          "source": "2652"
        },
        {
          "exhibit_num": 17,
          "bates": "PIGORS-F8-0017",
          "text_preview": "er curiam opinion of the Court of Appeals, issued March 12,\n2015 (Docket No. 323246)32 (finding that the trial cou",
          "source": "2653"
        },
        {
          "exhibit_num": 18,
          "bates": "PIGORS-F8-0018",
          "text_preview": "er curiam opinion of the Court of\nAppeals, issued March 12, 2015 (Docket No. 323246)104\n(finding that the trial co",
          "source": "2655"
        },
        {
          "exhibit_num": 19,
          "bates": "PIGORS-F8-0019",
          "text_preview": "pinion per curiam of the\nCourt of Appeals, issued March 12, 2015 (Docket No. 323246)3\n(finding that the trial cour",
          "source": "2681"
        },
        {
          "exhibit_num": 20,
          "bates": "PIGORS-F8-0020",
          "text_preview": "pinion per curiam of the Court of Appeals, issued March\n12, 2015 (Docket No. 323246)8 (finding that the trial cour",
          "source": "2690"
        }
      ]
    },
    "F9": {
      "name": "COA Appeal Brief",
      "exhibit_count": 20,
      "exhibits": [
        {
          "exhibit_num": 1,
          "bates": "PIGORS-F9-0001",
          "text_preview": "the Court.  He describes\n being  around\nthreaten  him, being  followed  and other  dangerous\nactivities.  These  situations\n are harmful  to the  child  and place  him at risk.\n* \nThe reasonable\n like",
          "source": "13"
        },
        {
          "exhibit_num": 2,
          "bates": "PIGORS-F9-0002",
          "text_preview": "the Court.  He describes  being  around\nrandom  men who beat him up and threaten  him, being  followed  and other  dangerous\nactivities.  These  situations  are harmful  to the child and place  him at",
          "source": "51"
        },
        {
          "exhibit_num": 3,
          "bates": "PIGORS-F9-0003",
          "text_preview": "hearing\n and  address  the  child's\nbest  interests\n within\n a reasonable\n time,  and  that  failure\n to comply\n with\nMCR  3.207's\n notice  and  heating\n requirements\n is error.  (FindLaw\n Case\nLaw)\no",
          "source": "77"
        },
        {
          "exhibit_num": 4,
          "bates": "PIGORS-F9-0004",
          "text_preview": "Court Rules. This marks at least the fourth  instance of  evasion de6gned :\nsuppress Plaintiffs  ability  to receive notice, present rebuttal, or obtain timely  relM.  \n;3'i\nThis  defect  is not  cler",
          "source": "237"
        },
        {
          "exhibit_num": 5,
          "bates": "PIGORS-F9-0005",
          "text_preview": "due process.\nAuthority:\n MCR  3.207(B);\n MCR  2.11 9; MCR  2.116(C)(8)-(10);\n U.S. Const.  amend.  XIV.\nRelief:  Motion\n must  be vacated  in full.\nII.  PROCEDURAL\n ABUSE  AND  RULE\n VIOLATION\n OBJECT",
          "source": "238"
        },
        {
          "exhibit_num": 6,
          "bates": "PIGORS-F9-0006",
          "text_preview": "notice, present rebuttal, or obtain timely  relM.  \n;3'i\nThis  defect  is not  clerical-it\n is a systematic\n abuse  of  the judicial\n process  to deny  access  to the\nforum  and obstruct  due process.",
          "source": "239"
        },
        {
          "exhibit_num": 7,
          "bates": "PIGORS-F9-0007",
          "text_preview": "Hearing:\n August\n 22, 2025\nSCRIPT\n FOR  THE  RECORD:\nYour  Honor,\nPursuant  to MRE  401-403,\n 901, 1001,  and 1002,  I respectfully\n ask the Court  to allow  me  to\nbriefly\n display  a visual  exhibit",
          "source": "240"
        },
        {
          "exhibit_num": 8,
          "bates": "PIGORS-F9-0008",
          "text_preview": "safety with Cody, citing substance abuse\nissues.\nMay 19, 2024: Emily refuses to test Lincoln for potential pean",
          "source": "511"
        },
        {
          "exhibit_num": 9,
          "bates": "PIGORS-F9-0009",
          "text_preview": "ge: The Honorable Jenny L. McNeill\nDate of Brief: February 11, 2026\nTABLE OF CONTENTS\nI. STATEMENT OF JURISDICTION\nII",
          "source": "2066"
        },
        {
          "exhibit_num": 10,
          "bates": "PIGORS-F9-0010",
          "text_preview": "order that is the subject of this appeal.\nB. The August 5, 2025 Ex Parte Suspension Order\nOn August 5, 2025, Fath",
          "source": "2070"
        },
        {
          "exhibit_num": 11,
          "bates": "PIGORS-F9-0011",
          "text_preview": "Father's parenting time should be restored to the July 17, 2024 baseline.\nC. THE TRIAL COURT ABUSED ITS DISCRETIO",
          "source": "2091"
        },
        {
          "exhibit_num": 12,
          "bates": "PIGORS-F9-0012",
          "text_preview": "appeals/applications/original proceedings (e.g., $375). Michigan Legislature\nPrinted using ChatGPT to P",
          "source": "2217"
        },
        {
          "exhibit_num": 13,
          "bates": "PIGORS-F9-0013",
          "text_preview": "cision of the Court of Appeals issued on or after November 1,\n1990, that has not been reversed or modified by the Su",
          "source": "2232"
        },
        {
          "exhibit_num": 14,
          "bates": "PIGORS-F9-0014",
          "text_preview": "cision of the Court of Appeals issued on or after November 1, 1990, that has\nnot been reversed or modified by the Su",
          "source": "2498"
        },
        {
          "exhibit_num": 15,
          "bates": "PIGORS-F9-0015",
          "text_preview": "er curiam opinion of\nthe Court of Appeals, issued October 28, 2008 (Docket No. 278470).",
          "source": "2499"
        },
        {
          "exhibit_num": 16,
          "bates": "PIGORS-F9-0016",
          "text_preview": "er curiam opinion\nof the Court of Appeals, issued October 28, 2008 (Docket\nNo. 278470).\nD.\nFines Must Generally be P",
          "source": "2527"
        },
        {
          "exhibit_num": 17,
          "bates": "PIGORS-F9-0017",
          "text_preview": "ing his\nchildren to another state. Id. at 335. On January 25, 2002, the Court of\nAppeals issued its decision in DeRo",
          "source": "2539"
        },
        {
          "exhibit_num": 18,
          "bates": "PIGORS-F9-0018",
          "text_preview": "han 90 days and may fine the person not more\nthan $500. MCL 764.15f(1)(e).\n64\u201c[A] prior Court of Appeals",
          "source": "2557"
        },
        {
          "exhibit_num": 19,
          "bates": "PIGORS-F9-0019",
          "text_preview": "r curiam opinion of the Court of Appeals, \nissued October 28, 2008 (Docket No. 278470) 4-8\nEx parte Terry, 128 US 28",
          "source": "2560"
        },
        {
          "exhibit_num": 20,
          "bates": "PIGORS-F9-0020",
          "text_preview": "cision of the Court of Appeals issued on or after November 1, \n1990, that has not been reversed or modified by the Su",
          "source": "2632"
        }
      ]
    },
    "F10": {
      "name": "AGC Grievance",
      "exhibit_count": 20,
      "exhibits": [
        {
          "exhibit_num": 1,
          "bates": "PIGORS-F10-0001",
          "text_preview": "HEARING\nEMILY\n WATSON,\nDefendant.\nAndrew\n Pigors\nSelf-Represented\n Litigant\nJennifer\n Batnes  (P55406)\nAttorney\n for  Defendant\nBoth  parties  appeared\n for  a Trial  regarding\n Custody,\n Parenting  T",
          "source": "34"
        },
        {
          "exhibit_num": 2,
          "bates": "PIGORS-F10-0002",
          "text_preview": "Hearing.\n01/07/2025\n \nD \n001  \nMSC\nSHOW  CAUSE\n \nHEARING\nNG  \nPLEA\n DEF  \nREQUESTED\n ATTORNEY\n01/07/2025\n \nP \n001  \nRNU\nORDER\nORDER\n ON  MOTION\n TO  MODIFY,\n \nEXTEND,\n \nOR  TERMINATE\n \nPERSONAL\n \nPROT",
          "source": "164"
        },
        {
          "exhibit_num": 3,
          "bates": "PIGORS-F10-0003",
          "text_preview": "HEARING\n \nON \nVIOLATION\n \nOF \nVALID\n \nPERSONAL\n \nPROTECTION\n \nFOREIGN\nPROTECTION\n ORDER\n01 /07/2025\n \nRNU\nREQUEST\n \nFOR  \nCOURT\n APPOINTED\n ATTORNEY\n AND  \nORDER\nREQUEST\n \nFOR  \nAPPOINTMENT\n OF \nATTOR",
          "source": "165"
        },
        {
          "exhibit_num": 4,
          "bates": "PIGORS-F10-0004",
          "text_preview": "Hearing.\n \nHearing\nAPPOINTED\n ATTORNEY\nD \n001\nAPPOINTED\n ATTORNEY\n AND  \nORDER\nCOURT\n APPOINTED\n ATTORNEY\nTO  \nSHOW  \nCAUSE\nTO  \nSHOW  \nCAUSE\n \nFOR \nVIOLATING\n \nVALID\n \nPERSONAL\n \nFOREIGN\nD\nSERVICE\nSE",
          "source": "170"
        },
        {
          "exhibit_num": 5,
          "bates": "PIGORS-F10-0005",
          "text_preview": "notice\n has  also  been  sent\n to:\nJENNIFER\n L.  \nBARNES\n \nA  \n55406\n ATTORNEY\n FOR  EMILY\n ANN  WATSON\nPTY NTF\nPARTY\n NOTIFICATION",
          "source": "177"
        },
        {
          "exhibit_num": 6,
          "bates": "PIGORS-F10-0006",
          "text_preview": "notice\n has  also  been  sent  to:\nJENNII'ER\n L.  \nBARNES\nA  \n55406\n ATTORNEY\n FOR  EMILY\n \nANN  \nWATSON\n-'.  NOT\nNOTICE\n TO  APPEAR",
          "source": "180"
        },
        {
          "exhibit_num": 7,
          "bates": "PIGORS-F10-0007",
          "text_preview": "notice\n has  also  been  sent  to:\nJENNIFER\n L.  \nBARNES\nA  \n55406\n ATTORNEY\n FOR  EMILY\n ANN  WATSON\nCC NOT\nNOTICE\n TO  APPEAR",
          "source": "182"
        },
        {
          "exhibit_num": 8,
          "bates": "PIGORS-F10-0008",
          "text_preview": "notice\n has  also  been  sent\n to:\nJENNIFER\n \nL.  \nBARNES\n \nA  \n55406\n ATTORNEY\n FOR  EMILY\n ANN \nWATSON\nPTY NTF\nPARTY\n NOTIFICATION",
          "source": "196"
        },
        {
          "exhibit_num": 9,
          "bates": "PIGORS-F10-0009",
          "text_preview": "NOTICE  FOR  ENTRY  OF ORDER\nAND  CERTIFICATE\n OF MAILING\nRECOMMENDATION\n AND  ORDER\nDISMISSING\n PARENTING\n TIME\nMOTION\nJENNIFER\n L BARNES\nATTORNEY\n AT LAW\njbarneslaw@aol.com\nPLEASE  TAKE  NOTICE:  Th",
          "source": "286"
        },
        {
          "exhibit_num": 10,
          "bates": "PIGORS-F10-0010",
          "text_preview": "granted.\nIT IS FURTHER ORDERED that Defendant's Attorney of Record shall\nrecalculate child support utilizing the following modifications: \nfor the child  support\ncalculations and corresponding Uniform",
          "source": "301"
        },
        {
          "exhibit_num": 11,
          "bates": "PIGORS-F10-0011",
          "text_preview": "ex parte\ncommunications,\n fair  opportunity\n to be heard).  (Michigan\n Courts)\nII.  SUMMARY\n OF  MISCONDUCT\nDrawing\n on my  compiled\n narrative,\n timeline,\n and  my  record,  the core  patteriis\n I ha",
          "source": "375"
        },
        {
          "exhibit_num": 12,
          "bates": "PIGORS-F10-0012",
          "text_preview": "ng, subjects the offending attorney or party to a $150 penalty to be paid in the\nmanner specified in the",
          "source": "416"
        },
        {
          "exhibit_num": 13,
          "bates": "PIGORS-F10-0013",
          "text_preview": "the offending attorney or party to an additional $150 penalty.\n(3) The case evaluation summary shall co",
          "source": "417"
        },
        {
          "exhibit_num": 14,
          "bates": "PIGORS-F10-0014",
          "text_preview": "\u2022 Void all custody modification orders\n\u2022 Restore July 17, 2024 custody order\n\u2022 Award attorney fees and costs\nStr",
          "source": "2053"
        },
        {
          "exhibit_num": 15,
          "bates": "PIGORS-F10-0015",
          "text_preview": "Damages: $50,000-100,000\nTotal Potential Damages: $200,000-400,000 (plus attorney fees under 42",
          "source": "2061"
        },
        {
          "exhibit_num": 16,
          "bates": "PIGORS-F10-0016",
          "text_preview": "comprehensive federal civil rights action seeking $200,000-\n400,000 in damages plus attorney fees. However,",
          "source": "2064"
        },
        {
          "exhibit_num": 17,
          "bates": "PIGORS-F10-0017",
          "text_preview": "ng, subjects the offending attorney\nor party to a $150 penalty to be paid in the manner specified in the",
          "source": "2294"
        },
        {
          "exhibit_num": 18,
          "bates": "PIGORS-F10-0018",
          "text_preview": "the\noffending attorney or party to an additional $150 penalty.\u201d MCR\n2.403(I)(2).\nF. Case Evaluation Dec",
          "source": "2295"
        },
        {
          "exhibit_num": 19,
          "bates": "PIGORS-F10-0019",
          "text_preview": "cial Institute\nNote: In OAG, 1995, No 6869, p 92 (September 6,\n1995),45 the Attorney General found that a school\nadmi",
          "source": "2638"
        },
        {
          "exhibit_num": 20,
          "bates": "PIGORS-F10-0020",
          "text_preview": "TION\n OF MISCONDUCT\".\nThe Time]ine  begins  with  May  15, 2023 (a]ready  heard by this  Court),  continues  thro",
          "source": "2739"
        }
      ]
    }
  }
}